Memora/__init__.py
Memora/app_error.py
Memora/config.py
Memora/builder/__init__.py
Memora/builder/commands/__init__.py
Memora/builder/commands/command.py
Memora/builder/commands/post_add.py
Memora/builder/commands/post_add_batch.py
Memora/builder/commands/post_delete.py
Memora/builder/commands/post_find.py
Memora/builder/commands/post_find_where.py
Memora/builder/commands/post_find_where_and.py
Memora/builder/commands/post_find_where_or.py
Memora/builder/executors/__init__.py
Memora/builder/executors/add_batch_executor.py
Memora/builder/executors/add_executor.py
Memora/builder/executors/delete_executor.py
Memora/builder/executors/find_executor.py
Memora/services/__init__.py
Memora/services/memoraFetch.py
memora-0.1.1.dist-info/METADATA
memora-0.1.1.dist-info/WHEEL
memora-0.1.1.dist-info/top_level.txt
memora-0.1.1.dist-info/RECORD
