Metadata-Version: 2.1
Name: memora
Version: 0.1.1
Summary: Memora's official Python library
Home-page: https://docs.usememora.app/python
Author: Memora
Author-email: hello@usememora.app
Classifier: Programming Language :: Python :: 3
Classifier: License :: OSI Approved :: MIT License
Classifier: Operating System :: OS Independent
Requires-Python: >=3.6
Requires-Dist: requests
